streamlit_ws_localstorage/__init__.py
streamlit_ws_localstorage/auth_redirect_server/__init__.py
streamlit_ws_localstorage/auth_redirect_server/auth_redirect_server.py
streamlit_ws_localstorage/auth_redirect_server/auth_util.py
streamlit_ws_localstorage/websocket_server/__init__.py
streamlit_ws_localstorage/websocket_server/websocket-echo-test.py
streamlit_ws_localstorage/websocket_server/ws_server.py
streamlit_ws_localstorage-1.0.6.dist-info/LICENSE
streamlit_ws_localstorage-1.0.6.dist-info/METADATA
streamlit_ws_localstorage-1.0.6.dist-info/WHEEL
streamlit_ws_localstorage-1.0.6.dist-info/top_level.txt
streamlit_ws_localstorage-1.0.6.dist-info/RECORD
