Metadata-Version: 2.1
Name: streamlit-ws-localstorage
Version: 1.0.6
Summary: A simple synchronous way of accessing localStorage from your Streamlit app.
Home-page: https://github.com/gagangoku/streamlit-ws-localstorage
Author: Gagandeep Singh
Author-email: gagan@heloprotocol.in
License: UNKNOWN
Download-URL: https://github.com/gagangoku/streamlit-ws-localstorage/archive/refs/tags/1.0.6.tar.gz
Keywords: python,websocket,cookies,localstorage,streamlit
Platform: UNKNOWN
Requires-Python: >=3.6
Requires-Dist: streamlit (>=0.86)
